marshmallow_toplevel/__init__.py
marshmallow_toplevel-0.1.3.dist-info/LICENSE
marshmallow_toplevel-0.1.3.dist-info/WHEEL
marshmallow_toplevel-0.1.3.dist-info/METADATA
marshmallow_toplevel-0.1.3.dist-info/RECORD
