Metadata-Version: 2.1
Name: marshmallow-toplevel
Version: 0.1.3
Summary: Validate top-level lists with all the power of marshmallow
Home-page: https://github.com/and-semakin/marshmallow-toplevel
License: MIT
Author: Andrey Semakin
Author-email: and-semakin@ya.ru
Requires-Python: >=3.6,<4.0
Classifier: License :: OSI Approved :: MIT License
Classifier: Programming Language :: Python :: 3
Classifier: Programming Language :: Python :: 3.6
Classifier: Programming Language :: Python :: 3.7
Classifier: Programming Language :: Python :: 3.8
Classifier: Programming Language :: Python :: 3.9
Requires-Dist: marshmallow (>=3.5,<4)
Project-URL: Documentation, https://github.com/and-semakin/marshmallow-toplevel
Project-URL: Repository, https://github.com/and-semakin/marshmallow-toplevel
